sqlitabase/__init__.py
sqlitabase/db.py
sqlitabase-0.0.1.dist-info/METADATA
sqlitabase-0.0.1.dist-info/WHEEL
sqlitabase-0.0.1.dist-info/RECORD
